<annotation>
	<folder>video-319s</folder>
	<filename>1-ColorImg-266.bmp</filename>
	<path>C:\Users\pj\Desktop\苹果标记数据\NearView-AppleData\PCDCol-1920\video-319s\1-ColorImg-266.bmp</path>
	<source>
		<database>Unknown</database>
	</source>
	<size>
		<width>1920</width>
		<height>1080</height>
		<depth>3</depth>
	</size>
	<segmented>0</segmented>
	<object>
		<name>obscuredbyleaves</name>
		<pose>Unspecified</pose>
		<truncated>0</truncated>
		<difficult>0</difficult>
		<bndbox>
			<xmin>177</xmin>
			<ymin>658</ymin>
			<xmax>287</xmax>
			<ymax>751</ymax>
		</bndbox>
	</object>
	<object>
		<name>obscuredbyfruit</name>
		<pose>Unspecified</pose>
		<truncated>0</truncated>
		<difficult>0</difficult>
		<bndbox>
			<xmin>121</xmin>
			<ymin>658</ymin>
			<xmax>197</xmax>
			<ymax>740</ymax>
		</bndbox>
	</object>
	<object>
		<name>obscuredbyleaves</name>
		<pose>Unspecified</pose>
		<truncated>0</truncated>
		<difficult>0</difficult>
		<bndbox>
			<xmin>315</xmin>
			<ymin>711</ymin>
			<xmax>411</xmax>
			<ymax>801</ymax>
		</bndbox>
	</object>
	<object>
		<name>obscuredbyleaves</name>
		<pose>Unspecified</pose>
		<truncated>0</truncated>
		<difficult>0</difficult>
		<bndbox>
			<xmin>287</xmin>
			<ymin>626</ymin>
			<xmax>376</xmax>
			<ymax>708</ymax>
		</bndbox>
	</object>
	<object>
		<name>obscuredbyleaves</name>
		<pose>Unspecified</pose>
		<truncated>0</truncated>
		<difficult>0</difficult>
		<bndbox>
			<xmin>421</xmin>
			<ymin>654</ymin>
			<xmax>504</xmax>
			<ymax>745</ymax>
		</bndbox>
	</object>
	<object>
		<name>obscuredbyleaves</name>
		<pose>Unspecified</pose>
		<truncated>0</truncated>
		<difficult>0</difficult>
		<bndbox>
			<xmin>452</xmin>
			<ymin>574</ymin>
			<xmax>529</xmax>
			<ymax>645</ymax>
		</bndbox>
	</object>
	<object>
		<name>obscuredbyfruit</name>
		<pose>Unspecified</pose>
		<truncated>0</truncated>
		<difficult>0</difficult>
		<bndbox>
			<xmin>485</xmin>
			<ymin>541</ymin>
			<xmax>562</xmax>
			<ymax>621</ymax>
		</bndbox>
	</object>
	<object>
		<name>obscuredbyleaves</name>
		<pose>Unspecified</pose>
		<truncated>0</truncated>
		<difficult>0</difficult>
		<bndbox>
			<xmin>354</xmin>
			<ymin>377</ymin>
			<xmax>443</xmax>
			<ymax>456</ymax>
		</bndbox>
	</object>
	<object>
		<name>obscuredbyleaves</name>
		<pose>Unspecified</pose>
		<truncated>0</truncated>
		<difficult>0</difficult>
		<bndbox>
			<xmin>281</xmin>
			<ymin>233</ymin>
			<xmax>366</xmax>
			<ymax>294</ymax>
		</bndbox>
	</object>
	<object>
		<name>singlefruit</name>
		<pose>Unspecified</pose>
		<truncated>0</truncated>
		<difficult>0</difficult>
		<bndbox>
			<xmin>23</xmin>
			<ymin>28</ymin>
			<xmax>152</xmax>
			<ymax>145</ymax>
		</bndbox>
	</object>
	<object>
		<name>singlefruit</name>
		<pose>Unspecified</pose>
		<truncated>0</truncated>
		<difficult>0</difficult>
		<bndbox>
			<xmin>143</xmin>
			<ymin>7</ymin>
			<xmax>252</xmax>
			<ymax>113</ymax>
		</bndbox>
	</object>
	<object>
		<name>obscuredbylimb</name>
		<pose>Unspecified</pose>
		<truncated>0</truncated>
		<difficult>0</difficult>
		<bndbox>
			<xmin>791</xmin>
			<ymin>427</ymin>
			<xmax>867</xmax>
			<ymax>511</ymax>
		</bndbox>
	</object>
	<object>
		<name>obscuredbyleaves</name>
		<pose>Unspecified</pose>
		<truncated>0</truncated>
		<difficult>0</difficult>
		<bndbox>
			<xmin>725</xmin>
			<ymin>418</ymin>
			<xmax>792</xmax>
			<ymax>492</ymax>
		</bndbox>
	</object>
	<object>
		<name>obscuredbyleaves</name>
		<pose>Unspecified</pose>
		<truncated>0</truncated>
		<difficult>0</difficult>
		<bndbox>
			<xmin>930</xmin>
			<ymin>114</ymin>
			<xmax>1025</xmax>
			<ymax>207</ymax>
		</bndbox>
	</object>
	<object>
		<name>obscuredbyleaves</name>
		<pose>Unspecified</pose>
		<truncated>0</truncated>
		<difficult>0</difficult>
		<bndbox>
			<xmin>1137</xmin>
			<ymin>161</ymin>
			<xmax>1239</xmax>
			<ymax>270</ymax>
		</bndbox>
	</object>
	<object>
		<name>singlefruit</name>
		<pose>Unspecified</pose>
		<truncated>0</truncated>
		<difficult>0</difficult>
		<bndbox>
			<xmin>1000</xmin>
			<ymin>889</ymin>
			<xmax>1081</xmax>
			<ymax>982</ymax>
		</bndbox>
	</object>
	<object>
		<name>obscuredbyleaves</name>
		<pose>Unspecified</pose>
		<truncated>0</truncated>
		<difficult>0</difficult>
		<bndbox>
			<xmin>942</xmin>
			<ymin>998</ymin>
			<xmax>1010</xmax>
			<ymax>1077</ymax>
		</bndbox>
	</object>
	<object>
		<name>obscuredbyleaves</name>
		<pose>Unspecified</pose>
		<truncated>0</truncated>
		<difficult>0</difficult>
		<bndbox>
			<xmin>1016</xmin>
			<ymin>647</ymin>
			<xmax>1088</xmax>
			<ymax>725</ymax>
		</bndbox>
	</object>
	<object>
		<name>singlefruit</name>
		<pose>Unspecified</pose>
		<truncated>0</truncated>
		<difficult>0</difficult>
		<bndbox>
			<xmin>1030</xmin>
			<ymin>569</ymin>
			<xmax>1106</xmax>
			<ymax>649</ymax>
		</bndbox>
	</object>
	<object>
		<name>obscuredbyleaves</name>
		<pose>Unspecified</pose>
		<truncated>0</truncated>
		<difficult>0</difficult>
		<bndbox>
			<xmin>1367</xmin>
			<ymin>282</ymin>
			<xmax>1459</xmax>
			<ymax>377</ymax>
		</bndbox>
	</object>
	<object>
		<name>obscuredbyleaves</name>
		<pose>Unspecified</pose>
		<truncated>0</truncated>
		<difficult>0</difficult>
		<bndbox>
			<xmin>1499</xmin>
			<ymin>218</ymin>
			<xmax>1604</xmax>
			<ymax>316</ymax>
		</bndbox>
	</object>
	<object>
		<name>obscuredbyleaves</name>
		<pose>Unspecified</pose>
		<truncated>0</truncated>
		<difficult>0</difficult>
		<bndbox>
			<xmin>1639</xmin>
			<ymin>33</ymin>
			<xmax>1744</xmax>
			<ymax>130</ymax>
		</bndbox>
	</object>
	<object>
		<name>obscuredbyleaves</name>
		<pose>Unspecified</pose>
		<truncated>0</truncated>
		<difficult>0</difficult>
		<bndbox>
			<xmin>1529</xmin>
			<ymin>18</ymin>
			<xmax>1631</xmax>
			<ymax>123</ymax>
		</bndbox>
	</object>
	<object>
		<name>obscuredbyleaves</name>
		<pose>Unspecified</pose>
		<truncated>0</truncated>
		<difficult>0</difficult>
		<bndbox>
			<xmin>1369</xmin>
			<ymin>796</ymin>
			<xmax>1468</xmax>
			<ymax>887</ymax>
		</bndbox>
	</object>
	<object>
		<name>obscuredbyleaves</name>
		<pose>Unspecified</pose>
		<truncated>0</truncated>
		<difficult>0</difficult>
		<bndbox>
			<xmin>1318</xmin>
			<ymin>722</ymin>
			<xmax>1402</xmax>
			<ymax>806</ymax>
		</bndbox>
	</object>
	<object>
		<name>obscuredbyleaves</name>
		<pose>Unspecified</pose>
		<truncated>0</truncated>
		<difficult>0</difficult>
		<bndbox>
			<xmin>1245</xmin>
			<ymin>779</ymin>
			<xmax>1314</xmax>
			<ymax>850</ymax>
		</bndbox>
	</object>
	<object>
		<name>obscuredbyleaves</name>
		<pose>Unspecified</pose>
		<truncated>0</truncated>
		<difficult>0</difficult>
		<bndbox>
			<xmin>1218</xmin>
			<ymin>659</ymin>
			<xmax>1295</xmax>
			<ymax>749</ymax>
		</bndbox>
	</object>
	<object>
		<name>singlefruit</name>
		<pose>Unspecified</pose>
		<truncated>0</truncated>
		<difficult>0</difficult>
		<bndbox>
			<xmin>1396</xmin>
			<ymin>637</ymin>
			<xmax>1490</xmax>
			<ymax>735</ymax>
		</bndbox>
	</object>
	<object>
		<name>obscuredbyleaves</name>
		<pose>Unspecified</pose>
		<truncated>0</truncated>
		<difficult>0</difficult>
		<bndbox>
			<xmin>1497</xmin>
			<ymin>601</ymin>
			<xmax>1593</xmax>
			<ymax>694</ymax>
		</bndbox>
	</object>
	<object>
		<name>obscuredbyleaves</name>
		<pose>Unspecified</pose>
		<truncated>0</truncated>
		<difficult>0</difficult>
		<bndbox>
			<xmin>1535</xmin>
			<ymin>737</ymin>
			<xmax>1629</xmax>
			<ymax>820</ymax>
		</bndbox>
	</object>
	<object>
		<name>singlefruit</name>
		<pose>Unspecified</pose>
		<truncated>0</truncated>
		<difficult>0</difficult>
		<bndbox>
			<xmin>1673</xmin>
			<ymin>656</ymin>
			<xmax>1787</xmax>
			<ymax>750</ymax>
		</bndbox>
	</object>
	<object>
		<name>obscuredbyfruit</name>
		<pose>Unspecified</pose>
		<truncated>0</truncated>
		<difficult>0</difficult>
		<bndbox>
			<xmin>1557</xmin>
			<ymin>550</ymin>
			<xmax>1644</xmax>
			<ymax>627</ymax>
		</bndbox>
	</object>
	<object>
		<name>obscuredbyfruit</name>
		<pose>Unspecified</pose>
		<truncated>0</truncated>
		<difficult>0</difficult>
		<bndbox>
			<xmin>1582</xmin>
			<ymin>794</ymin>
			<xmax>1669</xmax>
			<ymax>873</ymax>
		</bndbox>
	</object>
	<object>
		<name>obscuredbyfruit</name>
		<pose>Unspecified</pose>
		<truncated>0</truncated>
		<difficult>0</difficult>
		<bndbox>
			<xmin>55</xmin>
			<ymin>545</ymin>
			<xmax>131</xmax>
			<ymax>621</ymax>
		</bndbox>
	</object>
</annotation>