<annotation>
	<folder>picture</folder>
	<filename>ColorImg-367.bmp</filename>
	<path>C:\Users\pj\Desktop\苹果标记数据\NearView-AppleData\PCDCol-1920\video-192s\picture\ColorImg-367.bmp</path>
	<source>
		<database>Unknown</database>
	</source>
	<size>
		<width>1920</width>
		<height>1080</height>
		<depth>3</depth>
	</size>
	<segmented>0</segmented>
	<object>
		<name>obscuredbyleaves</name>
		<pose>Unspecified</pose>
		<truncated>0</truncated>
		<difficult>0</difficult>
		<bndbox>
			<xmin>290</xmin>
			<ymin>883</ymin>
			<xmax>391</xmax>
			<ymax>988</ymax>
		</bndbox>
	</object>
	<object>
		<name>obscuredbyleaves</name>
		<pose>Unspecified</pose>
		<truncated>0</truncated>
		<difficult>0</difficult>
		<bndbox>
			<xmin>206</xmin>
			<ymin>636</ymin>
			<xmax>301</xmax>
			<ymax>717</ymax>
		</bndbox>
	</object>
	<object>
		<name>obscuredbyleaves</name>
		<pose>Unspecified</pose>
		<truncated>0</truncated>
		<difficult>0</difficult>
		<bndbox>
			<xmin>295</xmin>
			<ymin>712</ymin>
			<xmax>383</xmax>
			<ymax>790</ymax>
		</bndbox>
	</object>
	<object>
		<name>obscuredbyfruit</name>
		<pose>Unspecified</pose>
		<truncated>0</truncated>
		<difficult>0</difficult>
		<bndbox>
			<xmin>404</xmin>
			<ymin>718</ymin>
			<xmax>500</xmax>
			<ymax>806</ymax>
		</bndbox>
	</object>
	<object>
		<name>obscuredbyleaves</name>
		<pose>Unspecified</pose>
		<truncated>0</truncated>
		<difficult>0</difficult>
		<bndbox>
			<xmin>842</xmin>
			<ymin>925</ymin>
			<xmax>918</xmax>
			<ymax>996</ymax>
		</bndbox>
	</object>
	<object>
		<name>singlefruit</name>
		<pose>Unspecified</pose>
		<truncated>0</truncated>
		<difficult>0</difficult>
		<bndbox>
			<xmin>871</xmin>
			<ymin>613</ymin>
			<xmax>950</xmax>
			<ymax>699</ymax>
		</bndbox>
	</object>
	<object>
		<name>obscuredbyleaves</name>
		<pose>Unspecified</pose>
		<truncated>0</truncated>
		<difficult>0</difficult>
		<bndbox>
			<xmin>852</xmin>
			<ymin>547</ymin>
			<xmax>928</xmax>
			<ymax>617</ymax>
		</bndbox>
	</object>
	<object>
		<name>obscuredbyleaves</name>
		<pose>Unspecified</pose>
		<truncated>0</truncated>
		<difficult>0</difficult>
		<bndbox>
			<xmin>809</xmin>
			<ymin>360</ymin>
			<xmax>882</xmax>
			<ymax>430</ymax>
		</bndbox>
	</object>
	<object>
		<name>obscuredbyleaves</name>
		<pose>Unspecified</pose>
		<truncated>0</truncated>
		<difficult>0</difficult>
		<bndbox>
			<xmin>1258</xmin>
			<ymin>746</ymin>
			<xmax>1338</xmax>
			<ymax>826</ymax>
		</bndbox>
	</object>
	<object>
		<name>obscuredbyleaves</name>
		<pose>Unspecified</pose>
		<truncated>0</truncated>
		<difficult>0</difficult>
		<bndbox>
			<xmin>1372</xmin>
			<ymin>782</ymin>
			<xmax>1461</xmax>
			<ymax>855</ymax>
		</bndbox>
	</object>
	<object>
		<name>obscuredbyleaves</name>
		<pose>Unspecified</pose>
		<truncated>0</truncated>
		<difficult>0</difficult>
		<bndbox>
			<xmin>1581</xmin>
			<ymin>963</ymin>
			<xmax>1650</xmax>
			<ymax>1027</ymax>
		</bndbox>
	</object>
	<object>
		<name>obscuredbyleaves</name>
		<pose>Unspecified</pose>
		<truncated>0</truncated>
		<difficult>0</difficult>
		<bndbox>
			<xmin>1302</xmin>
			<ymin>656</ymin>
			<xmax>1378</xmax>
			<ymax>711</ymax>
		</bndbox>
	</object>
	<object>
		<name>obscuredbylimb</name>
		<pose>Unspecified</pose>
		<truncated>0</truncated>
		<difficult>0</difficult>
		<bndbox>
			<xmin>1178</xmin>
			<ymin>571</ymin>
			<xmax>1267</xmax>
			<ymax>661</ymax>
		</bndbox>
	</object>
	<object>
		<name>obscuredbyleaves</name>
		<pose>Unspecified</pose>
		<truncated>0</truncated>
		<difficult>0</difficult>
		<bndbox>
			<xmin>681</xmin>
			<ymin>304</ymin>
			<xmax>759</xmax>
			<ymax>377</ymax>
		</bndbox>
	</object>
	<object>
		<name>obscuredbyleaves</name>
		<pose>Unspecified</pose>
		<truncated>0</truncated>
		<difficult>0</difficult>
		<bndbox>
			<xmin>576</xmin>
			<ymin>183</ymin>
			<xmax>681</xmax>
			<ymax>271</ymax>
		</bndbox>
	</object>
	<object>
		<name>obscuredbyfruit</name>
		<pose>Unspecified</pose>
		<truncated>0</truncated>
		<difficult>0</difficult>
		<bndbox>
			<xmin>628</xmin>
			<ymin>121</ymin>
			<xmax>723</xmax>
			<ymax>213</ymax>
		</bndbox>
	</object>
	<object>
		<name>obscuredbyleaves</name>
		<pose>Unspecified</pose>
		<truncated>0</truncated>
		<difficult>0</difficult>
		<bndbox>
			<xmin>302</xmin>
			<ymin>116</ymin>
			<xmax>371</xmax>
			<ymax>175</ymax>
		</bndbox>
	</object>
	<object>
		<name>obscuredbyleaves</name>
		<pose>Unspecified</pose>
		<truncated>0</truncated>
		<difficult>0</difficult>
		<bndbox>
			<xmin>769</xmin>
			<ymin>133</ymin>
			<xmax>873</xmax>
			<ymax>232</ymax>
		</bndbox>
	</object>
	<object>
		<name>obscuredbyleaves</name>
		<pose>Unspecified</pose>
		<truncated>0</truncated>
		<difficult>0</difficult>
		<bndbox>
			<xmin>1152</xmin>
			<ymin>182</ymin>
			<xmax>1225</xmax>
			<ymax>241</ymax>
		</bndbox>
	</object>
	<object>
		<name>obscuredbyfruit</name>
		<pose>Unspecified</pose>
		<truncated>0</truncated>
		<difficult>0</difficult>
		<bndbox>
			<xmin>1038</xmin>
			<ymin>20</ymin>
			<xmax>1134</xmax>
			<ymax>127</ymax>
		</bndbox>
	</object>
	<object>
		<name>obscuredbyleaves</name>
		<pose>Unspecified</pose>
		<truncated>0</truncated>
		<difficult>0</difficult>
		<bndbox>
			<xmin>1316</xmin>
			<ymin>66</ymin>
			<xmax>1416</xmax>
			<ymax>159</ymax>
		</bndbox>
	</object>
	<object>
		<name>singlefruit</name>
		<pose>Unspecified</pose>
		<truncated>0</truncated>
		<difficult>0</difficult>
		<bndbox>
			<xmin>1500</xmin>
			<ymin>507</ymin>
			<xmax>1591</xmax>
			<ymax>590</ymax>
		</bndbox>
	</object>
	<object>
		<name>obscuredbyleaves</name>
		<pose>Unspecified</pose>
		<truncated>0</truncated>
		<difficult>0</difficult>
		<bndbox>
			<xmin>1642</xmin>
			<ymin>502</ymin>
			<xmax>1744</xmax>
			<ymax>598</ymax>
		</bndbox>
	</object>
	<object>
		<name>obscuredbyleaves</name>
		<pose>Unspecified</pose>
		<truncated>0</truncated>
		<difficult>0</difficult>
		<bndbox>
			<xmin>1774</xmin>
			<ymin>442</ymin>
			<xmax>1866</xmax>
			<ymax>526</ymax>
		</bndbox>
	</object>
	<object>
		<name>obscuredbyleaves</name>
		<pose>Unspecified</pose>
		<truncated>0</truncated>
		<difficult>0</difficult>
		<bndbox>
			<xmin>1610</xmin>
			<ymin>413</ymin>
			<xmax>1706</xmax>
			<ymax>501</ymax>
		</bndbox>
	</object>
</annotation>