<annotation>
	<folder>video-319s</folder>
	<filename>1-ColorImg-219.bmp</filename>
	<path>C:\Users\pj\Desktop\苹果标记数据\NearView-AppleData\PCDCol-1920\video-319s\1-ColorImg-219.bmp</path>
	<source>
		<database>Unknown</database>
	</source>
	<size>
		<width>1920</width>
		<height>1080</height>
		<depth>3</depth>
	</size>
	<segmented>0</segmented>
	<object>
		<name>obscuredbyleaves</name>
		<pose>Unspecified</pose>
		<truncated>1</truncated>
		<difficult>0</difficult>
		<bndbox>
			<xmin>1810</xmin>
			<ymin>635</ymin>
			<xmax>1919</xmax>
			<ymax>737</ymax>
		</bndbox>
	</object>
	<object>
		<name>singlefruit</name>
		<pose>Unspecified</pose>
		<truncated>0</truncated>
		<difficult>0</difficult>
		<bndbox>
			<xmin>1704</xmin>
			<ymin>839</ymin>
			<xmax>1823</xmax>
			<ymax>940</ymax>
		</bndbox>
	</object>
	<object>
		<name>obscuredbyfruit</name>
		<pose>Unspecified</pose>
		<truncated>0</truncated>
		<difficult>0</difficult>
		<bndbox>
			<xmin>1786</xmin>
			<ymin>827</ymin>
			<xmax>1863</xmax>
			<ymax>927</ymax>
		</bndbox>
	</object>
	<object>
		<name>obscuredbyleaves</name>
		<pose>Unspecified</pose>
		<truncated>0</truncated>
		<difficult>0</difficult>
		<bndbox>
			<xmin>1320</xmin>
			<ymin>966</ymin>
			<xmax>1415</xmax>
			<ymax>1070</ymax>
		</bndbox>
	</object>
	<object>
		<name>obscuredbyleaves</name>
		<pose>Unspecified</pose>
		<truncated>0</truncated>
		<difficult>0</difficult>
		<bndbox>
			<xmin>1440</xmin>
			<ymin>989</ymin>
			<xmax>1533</xmax>
			<ymax>1075</ymax>
		</bndbox>
	</object>
	<object>
		<name>obscuredbyleaves</name>
		<pose>Unspecified</pose>
		<truncated>0</truncated>
		<difficult>0</difficult>
		<bndbox>
			<xmin>1320</xmin>
			<ymin>632</ymin>
			<xmax>1434</xmax>
			<ymax>750</ymax>
		</bndbox>
	</object>
	<object>
		<name>obscuredbyleaves</name>
		<pose>Unspecified</pose>
		<truncated>0</truncated>
		<difficult>0</difficult>
		<bndbox>
			<xmin>1719</xmin>
			<ymin>159</ymin>
			<xmax>1813</xmax>
			<ymax>247</ymax>
		</bndbox>
	</object>
	<object>
		<name>singlefruit</name>
		<pose>Unspecified</pose>
		<truncated>0</truncated>
		<difficult>0</difficult>
		<bndbox>
			<xmin>1281</xmin>
			<ymin>212</ymin>
			<xmax>1378</xmax>
			<ymax>311</ymax>
		</bndbox>
	</object>
	<object>
		<name>singlefruit</name>
		<pose>Unspecified</pose>
		<truncated>0</truncated>
		<difficult>0</difficult>
		<bndbox>
			<xmin>1052</xmin>
			<ymin>859</ymin>
			<xmax>1147</xmax>
			<ymax>978</ymax>
		</bndbox>
	</object>
	<object>
		<name>singlefruit</name>
		<pose>Unspecified</pose>
		<truncated>0</truncated>
		<difficult>0</difficult>
		<bndbox>
			<xmin>938</xmin>
			<ymin>652</ymin>
			<xmax>1040</xmax>
			<ymax>780</ymax>
		</bndbox>
	</object>
	<object>
		<name>obscuredbyleaves</name>
		<pose>Unspecified</pose>
		<truncated>0</truncated>
		<difficult>0</difficult>
		<bndbox>
			<xmin>1147</xmin>
			<ymin>535</ymin>
			<xmax>1242</xmax>
			<ymax>637</ymax>
		</bndbox>
	</object>
	<object>
		<name>singlefruit</name>
		<pose>Unspecified</pose>
		<truncated>0</truncated>
		<difficult>0</difficult>
		<bndbox>
			<xmin>1043</xmin>
			<ymin>454</ymin>
			<xmax>1130</xmax>
			<ymax>540</ymax>
		</bndbox>
	</object>
	<object>
		<name>singlefruit</name>
		<pose>Unspecified</pose>
		<truncated>0</truncated>
		<difficult>0</difficult>
		<bndbox>
			<xmin>1009</xmin>
			<ymin>222</ymin>
			<xmax>1104</xmax>
			<ymax>327</ymax>
		</bndbox>
	</object>
	<object>
		<name>obscuredbyleaves</name>
		<pose>Unspecified</pose>
		<truncated>0</truncated>
		<difficult>0</difficult>
		<bndbox>
			<xmin>1062</xmin>
			<ymin>116</ymin>
			<xmax>1158</xmax>
			<ymax>216</ymax>
		</bndbox>
	</object>
	<object>
		<name>obscuredbyleaves</name>
		<pose>Unspecified</pose>
		<truncated>0</truncated>
		<difficult>0</difficult>
		<bndbox>
			<xmin>938</xmin>
			<ymin>102</ymin>
			<xmax>1035</xmax>
			<ymax>185</ymax>
		</bndbox>
	</object>
	<object>
		<name>singlefruit</name>
		<pose>Unspecified</pose>
		<truncated>0</truncated>
		<difficult>0</difficult>
		<bndbox>
			<xmin>521</xmin>
			<ymin>682</ymin>
			<xmax>613</xmax>
			<ymax>782</ymax>
		</bndbox>
	</object>
	<object>
		<name>singlefruit</name>
		<pose>Unspecified</pose>
		<truncated>0</truncated>
		<difficult>0</difficult>
		<bndbox>
			<xmin>395</xmin>
			<ymin>601</ymin>
			<xmax>492</xmax>
			<ymax>689</ymax>
		</bndbox>
	</object>
	<object>
		<name>obscuredbyfruit</name>
		<pose>Unspecified</pose>
		<truncated>0</truncated>
		<difficult>0</difficult>
		<bndbox>
			<xmin>461</xmin>
			<ymin>547</ymin>
			<xmax>547</xmax>
			<ymax>627</ymax>
		</bndbox>
	</object>
	<object>
		<name>obscuredbyleaves</name>
		<pose>Unspecified</pose>
		<truncated>0</truncated>
		<difficult>0</difficult>
		<bndbox>
			<xmin>621</xmin>
			<ymin>740</ymin>
			<xmax>702</xmax>
			<ymax>796</ymax>
		</bndbox>
	</object>
</annotation>