<annotation>
	<folder>video-319s</folder>
	<filename>1-ColorImg-190.bmp</filename>
	<path>C:\Users\pj\Desktop\苹果标记数据\NearView-AppleData\PCDCol-1920\video-319s\1-ColorImg-190.bmp</path>
	<source>
		<database>Unknown</database>
	</source>
	<size>
		<width>1080</width>
		<height>1920</height>
		<depth>3</depth>
	</size>
	<segmented>0</segmented>
	<object>
		<name>obscuredbyleaves</name>
		<pose>Unspecified</pose>
		<truncated>0</truncated>
		<difficult>0</difficult>
		<bndbox>
			<xmin>913</xmin>
			<ymin>174</ymin>
			<xmax>966</xmax>
			<ymax>245</ymax>
		</bndbox>
	</object>
	<object>
		<name>singlefruit</name>
		<pose>Unspecified</pose>
		<truncated>0</truncated>
		<difficult>0</difficult>
		<bndbox>
			<xmin>851</xmin>
			<ymin>464</ymin>
			<xmax>941</xmax>
			<ymax>549</ymax>
		</bndbox>
	</object>
	<object>
		<name>obscuredbyleaves</name>
		<pose>Unspecified</pose>
		<truncated>0</truncated>
		<difficult>0</difficult>
		<bndbox>
			<xmin>864</xmin>
			<ymin>382</ymin>
			<xmax>949</xmax>
			<ymax>463</ymax>
		</bndbox>
	</object>
	<object>
		<name>obscuredbyleaves</name>
		<pose>Unspecified</pose>
		<truncated>0</truncated>
		<difficult>0</difficult>
		<bndbox>
			<xmin>761</xmin>
			<ymin>343</ymin>
			<xmax>844</xmax>
			<ymax>435</ymax>
		</bndbox>
	</object>
	<object>
		<name>obscuredbyleaves</name>
		<pose>Unspecified</pose>
		<truncated>0</truncated>
		<difficult>0</difficult>
		<bndbox>
			<xmin>688</xmin>
			<ymin>196</ymin>
			<xmax>768</xmax>
			<ymax>281</ymax>
		</bndbox>
	</object>
	<object>
		<name>obscuredbyleaves</name>
		<pose>Unspecified</pose>
		<truncated>0</truncated>
		<difficult>0</difficult>
		<bndbox>
			<xmin>487</xmin>
			<ymin>171</ymin>
			<xmax>542</xmax>
			<ymax>255</ymax>
		</bndbox>
	</object>
	<object>
		<name>obscuredbyleaves</name>
		<pose>Unspecified</pose>
		<truncated>0</truncated>
		<difficult>0</difficult>
		<bndbox>
			<xmin>316</xmin>
			<ymin>80</ymin>
			<xmax>380</xmax>
			<ymax>161</ymax>
		</bndbox>
	</object>
	<object>
		<name>obscuredbylimb</name>
		<pose>Unspecified</pose>
		<truncated>0</truncated>
		<difficult>0</difficult>
		<bndbox>
			<xmin>403</xmin>
			<ymin>201</ymin>
			<xmax>466</xmax>
			<ymax>287</ymax>
		</bndbox>
	</object>
	<object>
		<name>obscuredbylimb</name>
		<pose>Unspecified</pose>
		<truncated>0</truncated>
		<difficult>0</difficult>
		<bndbox>
			<xmin>363</xmin>
			<ymin>352</ymin>
			<xmax>420</xmax>
			<ymax>425</ymax>
		</bndbox>
	</object>
	<object>
		<name>obscuredbyleaves</name>
		<pose>Unspecified</pose>
		<truncated>0</truncated>
		<difficult>0</difficult>
		<bndbox>
			<xmin>314</xmin>
			<ymin>434</ymin>
			<xmax>389</xmax>
			<ymax>504</ymax>
		</bndbox>
	</object>
	<object>
		<name>singlefruit</name>
		<pose>Unspecified</pose>
		<truncated>0</truncated>
		<difficult>0</difficult>
		<bndbox>
			<xmin>7</xmin>
			<ymin>414</ymin>
			<xmax>96</xmax>
			<ymax>510</ymax>
		</bndbox>
	</object>
	<object>
		<name>obscuredbyleaves</name>
		<pose>Unspecified</pose>
		<truncated>0</truncated>
		<difficult>0</difficult>
		<bndbox>
			<xmin>693</xmin>
			<ymin>672</ymin>
			<xmax>766</xmax>
			<ymax>739</ymax>
		</bndbox>
	</object>
	<object>
		<name>obscuredbyleaves</name>
		<pose>Unspecified</pose>
		<truncated>0</truncated>
		<difficult>0</difficult>
		<bndbox>
			<xmin>565</xmin>
			<ymin>596</ymin>
			<xmax>649</xmax>
			<ymax>664</ymax>
		</bndbox>
	</object>
	<object>
		<name>obscuredbyleaves</name>
		<pose>Unspecified</pose>
		<truncated>0</truncated>
		<difficult>0</difficult>
		<bndbox>
			<xmin>502</xmin>
			<ymin>643</ymin>
			<xmax>585</xmax>
			<ymax>742</ymax>
		</bndbox>
	</object>
	<object>
		<name>obscuredbyleaves</name>
		<pose>Unspecified</pose>
		<truncated>0</truncated>
		<difficult>0</difficult>
		<bndbox>
			<xmin>164</xmin>
			<ymin>1064</ymin>
			<xmax>233</xmax>
			<ymax>1133</ymax>
		</bndbox>
	</object>
	<object>
		<name>obscuredbyleaves</name>
		<pose>Unspecified</pose>
		<truncated>0</truncated>
		<difficult>0</difficult>
		<bndbox>
			<xmin>166</xmin>
			<ymin>993</ymin>
			<xmax>239</xmax>
			<ymax>1061</ymax>
		</bndbox>
	</object>
	<object>
		<name>obscuredbylimb</name>
		<pose>Unspecified</pose>
		<truncated>0</truncated>
		<difficult>0</difficult>
		<bndbox>
			<xmin>352</xmin>
			<ymin>1053</ymin>
			<xmax>406</xmax>
			<ymax>1124</ymax>
		</bndbox>
	</object>
	<object>
		<name>singlefruit</name>
		<pose>Unspecified</pose>
		<truncated>0</truncated>
		<difficult>0</difficult>
		<bndbox>
			<xmin>821</xmin>
			<ymin>901</ymin>
			<xmax>921</xmax>
			<ymax>996</ymax>
		</bndbox>
	</object>
	<object>
		<name>singlefruit</name>
		<pose>Unspecified</pose>
		<truncated>0</truncated>
		<difficult>0</difficult>
		<bndbox>
			<xmin>751</xmin>
			<ymin>978</ymin>
			<xmax>863</xmax>
			<ymax>1071</ymax>
		</bndbox>
	</object>
	<object>
		<name>obscuredbyfruit</name>
		<pose>Unspecified</pose>
		<truncated>0</truncated>
		<difficult>0</difficult>
		<bndbox>
			<xmin>761</xmin>
			<ymin>897</ymin>
			<xmax>845</xmax>
			<ymax>976</ymax>
		</bndbox>
	</object>
	<object>
		<name>obscuredbyleaves</name>
		<pose>Unspecified</pose>
		<truncated>0</truncated>
		<difficult>0</difficult>
		<bndbox>
			<xmin>640</xmin>
			<ymin>1030</ymin>
			<xmax>723</xmax>
			<ymax>1107</ymax>
		</bndbox>
	</object>
	<object>
		<name>obscuredbyleaves</name>
		<pose>Unspecified</pose>
		<truncated>0</truncated>
		<difficult>0</difficult>
		<bndbox>
			<xmin>884</xmin>
			<ymin>1324</ymin>
			<xmax>949</xmax>
			<ymax>1387</ymax>
		</bndbox>
	</object>
	<object>
		<name>obscuredbyleaves</name>
		<pose>Unspecified</pose>
		<truncated>0</truncated>
		<difficult>0</difficult>
		<bndbox>
			<xmin>740</xmin>
			<ymin>1562</ymin>
			<xmax>855</xmax>
			<ymax>1681</ymax>
		</bndbox>
	</object>
	<object>
		<name>obscuredbyleaves</name>
		<pose>Unspecified</pose>
		<truncated>0</truncated>
		<difficult>0</difficult>
		<bndbox>
			<xmin>580</xmin>
			<ymin>1197</ymin>
			<xmax>678</xmax>
			<ymax>1291</ymax>
		</bndbox>
	</object>
	<object>
		<name>singlefruit</name>
		<pose>Unspecified</pose>
		<truncated>0</truncated>
		<difficult>0</difficult>
		<bndbox>
			<xmin>571</xmin>
			<ymin>1290</ymin>
			<xmax>665</xmax>
			<ymax>1385</ymax>
		</bndbox>
	</object>
	<object>
		<name>obscuredbyleaves</name>
		<pose>Unspecified</pose>
		<truncated>0</truncated>
		<difficult>0</difficult>
		<bndbox>
			<xmin>640</xmin>
			<ymin>1371</ymin>
			<xmax>716</xmax>
			<ymax>1461</ymax>
		</bndbox>
	</object>
	<object>
		<name>obscuredbyfruit</name>
		<pose>Unspecified</pose>
		<truncated>0</truncated>
		<difficult>0</difficult>
		<bndbox>
			<xmin>604</xmin>
			<ymin>1419</ymin>
			<xmax>698</xmax>
			<ymax>1509</ymax>
		</bndbox>
	</object>
</annotation>