<annotation>
	<folder>picture</folder>
	<filename>ColorImg-1B.bmp</filename>
	<path>C:\Users\pj\Desktop\苹果标记数据\NearView-AppleData\PCDCol-1920\video-148s\picture\ColorImg-1B.bmp</path>
	<source>
		<database>Unknown</database>
	</source>
	<size>
		<width>1080</width>
		<height>1920</height>
		<depth>3</depth>
	</size>
	<segmented>0</segmented>
	<object>
		<name>singlefruit</name>
		<pose>Unspecified</pose>
		<truncated>0</truncated>
		<difficult>0</difficult>
		<bndbox>
			<xmin>794</xmin>
			<ymin>264</ymin>
			<xmax>902</xmax>
			<ymax>374</ymax>
		</bndbox>
	</object>
	<object>
		<name>obscuredbyfruit</name>
		<pose>Unspecified</pose>
		<truncated>0</truncated>
		<difficult>0</difficult>
		<bndbox>
			<xmin>796</xmin>
			<ymin>197</ymin>
			<xmax>889</xmax>
			<ymax>290</ymax>
		</bndbox>
	</object>
	<object>
		<name>obscuredbyleaves</name>
		<pose>Unspecified</pose>
		<truncated>0</truncated>
		<difficult>0</difficult>
		<bndbox>
			<xmin>813</xmin>
			<ymin>525</ymin>
			<xmax>899</xmax>
			<ymax>609</ymax>
		</bndbox>
	</object>
	<object>
		<name>obscuredbyleaves</name>
		<pose>Unspecified</pose>
		<truncated>0</truncated>
		<difficult>0</difficult>
		<bndbox>
			<xmin>882</xmin>
			<ymin>697</ymin>
			<xmax>964</xmax>
			<ymax>763</ymax>
		</bndbox>
	</object>
	<object>
		<name>obscuredbyleaves</name>
		<pose>Unspecified</pose>
		<truncated>0</truncated>
		<difficult>0</difficult>
		<bndbox>
			<xmin>775</xmin>
			<ymin>719</ymin>
			<xmax>855</xmax>
			<ymax>793</ymax>
		</bndbox>
	</object>
	<object>
		<name>singlefruit</name>
		<pose>Unspecified</pose>
		<truncated>0</truncated>
		<difficult>0</difficult>
		<bndbox>
			<xmin>859</xmin>
			<ymin>777</ymin>
			<xmax>945</xmax>
			<ymax>859</ymax>
		</bndbox>
	</object>
	<object>
		<name>singlefruit</name>
		<pose>Unspecified</pose>
		<truncated>0</truncated>
		<difficult>0</difficult>
		<bndbox>
			<xmin>849</xmin>
			<ymin>910</ymin>
			<xmax>941</xmax>
			<ymax>993</ymax>
		</bndbox>
	</object>
	<object>
		<name>obscuredbyleaves</name>
		<pose>Unspecified</pose>
		<truncated>0</truncated>
		<difficult>0</difficult>
		<bndbox>
			<xmin>785</xmin>
			<ymin>834</ymin>
			<xmax>859</xmax>
			<ymax>905</ymax>
		</bndbox>
	</object>
	<object>
		<name>obscuredbyleaves</name>
		<pose>Unspecified</pose>
		<truncated>0</truncated>
		<difficult>0</difficult>
		<bndbox>
			<xmin>779</xmin>
			<ymin>896</ymin>
			<xmax>850</xmax>
			<ymax>973</ymax>
		</bndbox>
	</object>
	<object>
		<name>obscuredbylimb</name>
		<pose>Unspecified</pose>
		<truncated>0</truncated>
		<difficult>0</difficult>
		<bndbox>
			<xmin>826</xmin>
			<ymin>1030</ymin>
			<xmax>899</xmax>
			<ymax>1093</ymax>
		</bndbox>
	</object>
	<object>
		<name>singlefruit</name>
		<pose>Unspecified</pose>
		<truncated>0</truncated>
		<difficult>0</difficult>
		<bndbox>
			<xmin>858</xmin>
			<ymin>1277</ymin>
			<xmax>931</xmax>
			<ymax>1350</ymax>
		</bndbox>
	</object>
	<object>
		<name>singlefruit</name>
		<pose>Unspecified</pose>
		<truncated>0</truncated>
		<difficult>0</difficult>
		<bndbox>
			<xmin>821</xmin>
			<ymin>1340</ymin>
			<xmax>909</xmax>
			<ymax>1421</ymax>
		</bndbox>
	</object>
	<object>
		<name>obscuredbyleaves</name>
		<pose>Unspecified</pose>
		<truncated>0</truncated>
		<difficult>0</difficult>
		<bndbox>
			<xmin>758</xmin>
			<ymin>1478</ymin>
			<xmax>836</xmax>
			<ymax>1555</ymax>
		</bndbox>
	</object>
	<object>
		<name>obscuredbyleaves</name>
		<pose>Unspecified</pose>
		<truncated>0</truncated>
		<difficult>0</difficult>
		<bndbox>
			<xmin>761</xmin>
			<ymin>1248</ymin>
			<xmax>823</xmax>
			<ymax>1330</ymax>
		</bndbox>
	</object>
	<object>
		<name>obscuredbyleaves</name>
		<pose>Unspecified</pose>
		<truncated>0</truncated>
		<difficult>0</difficult>
		<bndbox>
			<xmin>484</xmin>
			<ymin>561</ymin>
			<xmax>552</xmax>
			<ymax>630</ymax>
		</bndbox>
	</object>
	<object>
		<name>obscuredbyleaves</name>
		<pose>Unspecified</pose>
		<truncated>0</truncated>
		<difficult>0</difficult>
		<bndbox>
			<xmin>206</xmin>
			<ymin>615</ymin>
			<xmax>296</xmax>
			<ymax>701</ymax>
		</bndbox>
	</object>
	<object>
		<name>obscuredbyleaves</name>
		<pose>Unspecified</pose>
		<truncated>0</truncated>
		<difficult>0</difficult>
		<bndbox>
			<xmin>213</xmin>
			<ymin>697</ymin>
			<xmax>313</xmax>
			<ymax>807</ymax>
		</bndbox>
	</object>
	<object>
		<name>obscuredbyleaves</name>
		<pose>Unspecified</pose>
		<truncated>0</truncated>
		<difficult>0</difficult>
		<bndbox>
			<xmin>396</xmin>
			<ymin>931</ymin>
			<xmax>466</xmax>
			<ymax>1004</ymax>
		</bndbox>
	</object>
	<object>
		<name>singlefruit</name>
		<pose>Unspecified</pose>
		<truncated>0</truncated>
		<difficult>0</difficult>
		<bndbox>
			<xmin>326</xmin>
			<ymin>988</ymin>
			<xmax>420</xmax>
			<ymax>1066</ymax>
		</bndbox>
	</object>
	<object>
		<name>obscuredbyfruit</name>
		<pose>Unspecified</pose>
		<truncated>0</truncated>
		<difficult>0</difficult>
		<bndbox>
			<xmin>298</xmin>
			<ymin>969</ymin>
			<xmax>369</xmax>
			<ymax>1040</ymax>
		</bndbox>
	</object>
	<object>
		<name>obscuredbyleaves</name>
		<pose>Unspecified</pose>
		<truncated>0</truncated>
		<difficult>0</difficult>
		<bndbox>
			<xmin>256</xmin>
			<ymin>1145</ymin>
			<xmax>326</xmax>
			<ymax>1205</ymax>
		</bndbox>
	</object>
	<object>
		<name>obscuredbyleaves</name>
		<pose>Unspecified</pose>
		<truncated>0</truncated>
		<difficult>0</difficult>
		<bndbox>
			<xmin>279</xmin>
			<ymin>1205</ymin>
			<xmax>358</xmax>
			<ymax>1295</ymax>
		</bndbox>
	</object>
	<object>
		<name>obscuredbyleaves</name>
		<pose>Unspecified</pose>
		<truncated>0</truncated>
		<difficult>0</difficult>
		<bndbox>
			<xmin>144</xmin>
			<ymin>1005</ymin>
			<xmax>202</xmax>
			<ymax>1061</ymax>
		</bndbox>
	</object>
	<object>
		<name>singlefruit</name>
		<pose>Unspecified</pose>
		<truncated>0</truncated>
		<difficult>0</difficult>
		<bndbox>
			<xmin>56</xmin>
			<ymin>1373</ymin>
			<xmax>145</xmax>
			<ymax>1463</ymax>
		</bndbox>
	</object>
	<object>
		<name>obscuredbyleaves</name>
		<pose>Unspecified</pose>
		<truncated>0</truncated>
		<difficult>0</difficult>
		<bndbox>
			<xmin>274</xmin>
			<ymin>1588</ymin>
			<xmax>373</xmax>
			<ymax>1697</ymax>
		</bndbox>
	</object>
	<object>
		<name>obscuredbyleaves</name>
		<pose>Unspecified</pose>
		<truncated>0</truncated>
		<difficult>0</difficult>
		<bndbox>
			<xmin>255</xmin>
			<ymin>1406</ymin>
			<xmax>328</xmax>
			<ymax>1465</ymax>
		</bndbox>
	</object>
</annotation>